<?xml version="1.0" encoding="utf-8"?>
<RunReport>
  <version>2</version>
  <runGuid>a0132130-d40b-4b7b-b9c0-2d48feb4b1d4</runGuid>
  <gameModeName>ClassicRun</gameModeName>
  <gameEnding>StandardLoss</gameEnding>
  <seed>13023953929463407135</seed>
  <runStartTimeUtc>5250027300197999992</runStartTimeUtc>
  <snapshotTimeUtc>5250027320921573660</snapshotTimeUtc>
  <snapshotRunTime>1837.248</snapshotRunTime>
  <runStopwatchValue>1827.71</runStopwatchValue>
  <ruleBook>Difficulty.Normal Expansions.DLC1.Off Artifacts.Bomb.Off Artifacts.Command.Off Artifacts.EliteOnly.Off Artifacts.Enigma.Off Artifacts.FriendlyFire.Off Artifacts.Glass.Off Artifacts.MixEnemy.Off Artifacts.MonsterTeamGainsItems.Off Artifacts.RandomSurvivorOnRespawn.Off Artifacts.Sacrifice.Off Artifacts.ShadowClone.Off Artifacts.SingleMonsterType.Off Artifacts.Swarms.Off Artifacts.TeamDeath.Off Artifacts.WeakAssKnees.Off Artifacts.WispOnDeath.Off Items.ArmorPlate.On Items.AttackSpeedAndMoveSpeed.Off Items.BarrierOnKill.On Items.Bear.On Items.BleedOnHit.On Items.BossDamageBonus.On Items.CritGlasses.On Items.Crowbar.On Items.Firework.Off Items.FlatHealth.On Items.FragileDamageBonus.Off Items.GoldOnHurt.Off Items.HealWhileSafe.On Items.HealingPotion.Off Items.Hoof.On Items.IgniteOnKill.On Items.Medkit.On Items.Mushroom.On Items.NearbyDamageBonus.On Items.OutOfCombatArmor.Off Items.PersonalShield.On Items.ScrapWhite.On Items.SecondarySkillMagazine.Off Items.SprintBonus.On Items.StickyBomb.On Items.StunChanceOnHit.On Items.Syringe.On Items.Tooth.On Items.TreasureCache.On Items.WardOnLevel.On Items.AttackSpeedOnCrit.Off Items.Bandolier.On Items.BonusGoldPackOnKill.On Items.ChainLightning.On Items.DeathMark.On Items.EnergizedOnEquipmentUse.Off Items.EquipmentMagazine.On Items.ExecuteLowHealthElite.Off Items.ExplodeOnDeath.On Items.Feather.On Items.FireRing.Off Items.FreeChest.Off Items.HealOnCrit.Off Items.IceRing.Off Items.Infusion.On Items.JumpBoost.On Items.Missile.On Items.MoveSpeedOnKill.Off Items.Phasing.On Items.PrimarySkillShuriken.Off Items.RegeneratingScrap.Off Items.ScrapGreen.On Items.Seed.On Items.SlowOnHit.On Items.SprintArmor.On Items.SprintOutOfCombat.On Items.Squid.Off Items.StrengthenBurn.Off Items.TPHealingNova.On Items.Thorns.On Items.WarCryOnMultiKill.Off Items.AlienHead.On Items.ArmorReductionOnHit.On Items.BarrierOnOverHeal.On Items.Behemoth.On Items.BounceNearby.On Items.CaptainDefenseMatrix.On Items.Clover.Off Items.CritDamage.Off Items.Dagger.On Items.DroneWeapons.Off Items.ExtraLife.On Items.FallBoots.On Items.GhostOnKill.On Items.HeadHunter.On Items.Icicle.On Items.ImmuneToDebuff.Off Items.IncreaseHealing.Off Items.KillEliteFrenzy.Off Items.LaserTurbine.On Items.MoreMissile.Off Items.NovaOnHeal.Off Items.PermanentDebuffOnHit.Off Items.Plant.On Items.RandomEquipmentTrigger.Off Items.ScrapRed.On Items.ShockNearby.On Items.Talisman.Off Items.UtilitySkillMagazine.On Items.AutoCastEquipment.Off Items.FocusConvergence.On Items.GoldOnHit.On Items.HalfAttackSpeedHalfCooldowns.Off Items.HalfSpeedDoubleHealth.Off Items.LunarBadLuck.Off Items.LunarDagger.On Items.LunarPrimaryReplacement.On Items.LunarSecondaryReplacement.On Items.LunarSpecialReplacement.On Items.LunarSun.Off Items.LunarTrinket.On Items.LunarUtilityReplacement.On Items.MonstersOnShrineUse.On Items.RandomDamageZone.On Items.RandomlyLunar.Off Items.RepeatHeal.On Items.ShieldOnly.On Items.ArtifactKey.On Items.BeetleGland.On Items.BleedOnHitAndExplode.On Items.FireballsOnHit.On Items.Knurl.On Items.LightningStrikeOnHit.On Items.MinorConstructOnKill.Off Items.NovaOnLowHealth.On Items.ParentEgg.On Items.Pearl.On Items.RoboBallBuddy.On Items.ScrapYellow.On Items.ShinyPearl.On Items.SiphonOnLowHealth.On Items.SprintWisp.On Items.TitanGoldDuringTP.On Items.BearVoid.Off Items.BleedOnHitVoid.Off Items.CritGlassesVoid.Off Items.MushroomVoid.Off Items.TreasureCacheVoid.Off Items.ChainLightningVoid.Off Items.ElementalRingVoid.Off Items.EquipmentMagazineVoid.Off Items.ExplodeOnDeathVoid.Off Items.MissileVoid.Off Items.SlowOnHitVoid.Off Items.CloverVoid.Off Items.ExtraLifeVoid.Off Items.VoidMegaCrabItem.Off Equipment.BFG.Off Equipment.Blackhole.On Equipment.BossHunter.Off Equipment.BurnNearby.On Equipment.Cleanse.Off Equipment.CommandMissile.On Equipment.CrippleWard.On Equipment.CritOnUse.On Equipment.DeathProjectile.Off Equipment.DroneBackup.Off Equipment.FireBallDash.On Equipment.Fruit.On Equipment.GainArmor.On Equipment.Gateway.Off Equipment.GoldGat.On Equipment.GummyClone.Off Equipment.Jetpack.On Equipment.LifestealOnHit.On Equipment.Lightning.Off Equipment.Meteor.Off Equipment.Molotov.Off Equipment.MultiShopCard.Off Equipment.PassiveHealing.Off Equipment.Recycle.On Equipment.Saw.On Equipment.Scanner.Off Equipment.TeamWarCry.On Equipment.Tonic.Off Equipment.VendingMachine.Off Misc.StartingMoney.15 Misc.StageOrder.Normal Misc.KeepMoneyBetweenStages.Off Misc.AllowDropIn.Off</ruleBook>
  <playerInfos>
    <PlayerInfo>
      <name>BingleDerryDan</name>
      <bodyName>CommandoBody</bodyName>
      <killerBodyName>GreaterWispBody</killerBodyName>
      <isDead>1</isDead>
      <statSheet>
        <fields>
          <totalGamesPlayed>1</totalGamesPlayed>
          <totalTimeAlive>1825.16676185653</totalTimeAlive>
          <totalKills>342</totalKills>
          <totalDeaths>1</totalDeaths>
          <totalDamageDealt>179582</totalDamageDealt>
          <totalDamageTaken>4402</totalDamageTaken>
          <totalHealthHealed>1461</totalHealthHealed>
          <highestDamageDealt>599</highestDamageDealt>
          <highestLevel>14</highestLevel>
          <totalGoldCollected>7681</totalGoldCollected>
          <maxGoldCollected>7681</maxGoldCollected>
          <totalDistanceTraveled>23796.135030347</totalDistanceTraveled>
          <totalItemsCollected>34</totalItemsCollected>
          <highestItemsCollected>34</highestItemsCollected>
          <totalStagesCompleted>3</totalStagesCompleted>
          <highestStagesCompleted>3</highestStagesCompleted>
          <totalPurchases>41</totalPurchases>
          <highestPurchases>41</highestPurchases>
          <totalGoldPurchases>39</totalGoldPurchases>
          <highestGoldPurchases>39</highestGoldPurchases>
          <totalTier2Purchases>1</totalTier2Purchases>
          <highestTier2Purchases>1</highestTier2Purchases>
          <totalDronesPurchased>1</totalDronesPurchased>
          <totalGreenSoupsPurchased>1</totalGreenSoupsPurchased>
          <totalEliteKills>30</totalEliteKills>
          <totalTeleporterBossKillsWitnessed>4</totalTeleporterBossKillsWitnessed>
          <totalTimeAlive.CommandoBody>1825.11676185392</totalTimeAlive.CommandoBody>
          <longestRun.CommandoBody>1827.71020507813</longestRun.CommandoBody>
          <damageDealtTo.BeetleBody>40344</damageDealtTo.BeetleBody>
          <damageDealtTo.BeetleGuardBody>30002</damageDealtTo.BeetleGuardBody>
          <damageDealtTo.BeetleQueen2Body>5217</damageDealtTo.BeetleQueen2Body>
          <damageDealtTo.BeetleWard>76</damageDealtTo.BeetleWard>
          <damageDealtTo.BellBody>667</damageDealtTo.BellBody>
          <damageDealtTo.ClayBossBody>21889</damageDealtTo.ClayBossBody>
          <damageDealtTo.GolemBody>14882</damageDealtTo.GolemBody>
          <damageDealtTo.GreaterWispBody>8733</damageDealtTo.GreaterWispBody>
          <damageDealtTo.ImpBody>18318</damageDealtTo.ImpBody>
          <damageDealtTo.JellyfishBody>3605</damageDealtTo.JellyfishBody>
          <damageDealtTo.LemurianBody>13188</damageDealtTo.LemurianBody>
          <damageDealtTo.LemurianBruiserBody>3425</damageDealtTo.LemurianBruiserBody>
          <damageDealtTo.MiniMushroomBody>3221</damageDealtTo.MiniMushroomBody>
          <damageDealtTo.TitanBody>3290</damageDealtTo.TitanBody>
          <damageDealtTo.WispBody>12725</damageDealtTo.WispBody>
          <damageDealtAs.CommandoBody>179582</damageDealtAs.CommandoBody>
          <damageTakenFrom.BeetleBody>166</damageTakenFrom.BeetleBody>
          <damageTakenFrom.BeetleGuardBody>503</damageTakenFrom.BeetleGuardBody>
          <damageTakenFrom.BeetleQueen2Body>76</damageTakenFrom.BeetleQueen2Body>
          <damageTakenFrom.ClayBossBody>369</damageTakenFrom.ClayBossBody>
          <damageTakenFrom.GolemBody>352</damageTakenFrom.GolemBody>
          <damageTakenFrom.GreaterWispBody>570</damageTakenFrom.GreaterWispBody>
          <damageTakenFrom.ImpBody>381</damageTakenFrom.ImpBody>
          <damageTakenFrom.JellyfishBody>39</damageTakenFrom.JellyfishBody>
          <damageTakenFrom.LemurianBody>563</damageTakenFrom.LemurianBody>
          <damageTakenFrom.LemurianBruiserBody>128</damageTakenFrom.LemurianBruiserBody>
          <damageTakenFrom.MiniMushroomBody>25</damageTakenFrom.MiniMushroomBody>
          <damageTakenFrom.TitanBody>101</damageTakenFrom.TitanBody>
          <damageTakenFrom.WispBody>133</damageTakenFrom.WispBody>
          <damageTakenAs.CommandoBody>4402</damageTakenAs.CommandoBody>
          <killsAgainst.BeetleBody>126</killsAgainst.BeetleBody>
          <killsAgainst.BeetleGuardBody>18</killsAgainst.BeetleGuardBody>
          <killsAgainst.BeetleQueen2Body>1</killsAgainst.BeetleQueen2Body>
          <killsAgainst.BellBody>1</killsAgainst.BellBody>
          <killsAgainst.ClayBossBody>2</killsAgainst.ClayBossBody>
          <killsAgainst.GolemBody>5</killsAgainst.GolemBody>
          <killsAgainst.GreaterWispBody>2</killsAgainst.GreaterWispBody>
          <killsAgainst.ImpBody>30</killsAgainst.ImpBody>
          <killsAgainst.JellyfishBody>13</killsAgainst.JellyfishBody>
          <killsAgainst.LemurianBody>52</killsAgainst.LemurianBody>
          <killsAgainst.MiniMushroomBody>2</killsAgainst.MiniMushroomBody>
          <killsAgainst.TitanBody>1</killsAgainst.TitanBody>
          <killsAgainst.WispBody>89</killsAgainst.WispBody>
          <killsAgainstElite.BeetleBody>16</killsAgainstElite.BeetleBody>
          <killsAgainstElite.GolemBody>1</killsAgainstElite.GolemBody>
          <killsAgainstElite.LemurianBody>4</killsAgainstElite.LemurianBody>
          <killsAgainstElite.WispBody>9</killsAgainstElite.WispBody>
          <deathsFrom.GreaterWispBody>1</deathsFrom.GreaterWispBody>
          <killsAs.CommandoBody>342</killsAs.CommandoBody>
          <deathsAs.CommandoBody>1</deathsAs.CommandoBody>
          <timesPicked.CommandoBody>1</timesPicked.CommandoBody>
          <totalCollected.Bandolier>2</totalCollected.Bandolier>
          <totalCollected.BarrierOnKill>2</totalCollected.BarrierOnKill>
          <totalCollected.BleedOnHit>1</totalCollected.BleedOnHit>
          <totalCollected.BonusGoldPackOnKill>1</totalCollected.BonusGoldPackOnKill>
          <totalCollected.BossDamageBonus>2</totalCollected.BossDamageBonus>
          <totalCollected.ChainLightning>1</totalCollected.ChainLightning>
          <totalCollected.CritGlasses>1</totalCollected.CritGlasses>
          <totalCollected.Crowbar>1</totalCollected.Crowbar>
          <totalCollected.DeathMark>1</totalCollected.DeathMark>
          <totalCollected.FlatHealth>1</totalCollected.FlatHealth>
          <totalCollected.HealWhileSafe>1</totalCollected.HealWhileSafe>
          <totalCollected.IgniteOnKill>2</totalCollected.IgniteOnKill>
          <totalCollected.Mushroom>2</totalCollected.Mushroom>
          <totalCollected.PersonalShield>2</totalCollected.PersonalShield>
          <totalCollected.ScrapGreen>1</totalCollected.ScrapGreen>
          <totalCollected.ScrapWhite>1</totalCollected.ScrapWhite>
          <totalCollected.SlowOnHit>2</totalCollected.SlowOnHit>
          <totalCollected.SprintArmor>1</totalCollected.SprintArmor>
          <totalCollected.SprintBonus>1</totalCollected.SprintBonus>
          <totalCollected.StickyBomb>1</totalCollected.StickyBomb>
          <totalCollected.StunChanceOnHit>3</totalCollected.StunChanceOnHit>
          <totalCollected.Syringe>2</totalCollected.Syringe>
          <totalCollected.Thorns>1</totalCollected.Thorns>
          <totalCollected.WardOnLevel>1</totalCollected.WardOnLevel>
          <highestCollected.Bandolier>2</highestCollected.Bandolier>
          <highestCollected.BarrierOnKill>2</highestCollected.BarrierOnKill>
          <highestCollected.BleedOnHit>1</highestCollected.BleedOnHit>
          <highestCollected.BonusGoldPackOnKill>1</highestCollected.BonusGoldPackOnKill>
          <highestCollected.BossDamageBonus>2</highestCollected.BossDamageBonus>
          <highestCollected.ChainLightning>1</highestCollected.ChainLightning>
          <highestCollected.CritGlasses>1</highestCollected.CritGlasses>
          <highestCollected.Crowbar>1</highestCollected.Crowbar>
          <highestCollected.DeathMark>1</highestCollected.DeathMark>
          <highestCollected.FlatHealth>1</highestCollected.FlatHealth>
          <highestCollected.HealWhileSafe>1</highestCollected.HealWhileSafe>
          <highestCollected.IgniteOnKill>2</highestCollected.IgniteOnKill>
          <highestCollected.Mushroom>2</highestCollected.Mushroom>
          <highestCollected.PersonalShield>2</highestCollected.PersonalShield>
          <highestCollected.ScrapGreen>1</highestCollected.ScrapGreen>
          <highestCollected.ScrapWhite>1</highestCollected.ScrapWhite>
          <highestCollected.SlowOnHit>2</highestCollected.SlowOnHit>
          <highestCollected.SprintArmor>1</highestCollected.SprintArmor>
          <highestCollected.SprintBonus>1</highestCollected.SprintBonus>
          <highestCollected.StickyBomb>1</highestCollected.StickyBomb>
          <highestCollected.StunChanceOnHit>3</highestCollected.StunChanceOnHit>
          <highestCollected.Syringe>2</highestCollected.Syringe>
          <highestCollected.Thorns>1</highestCollected.Thorns>
          <highestCollected.WardOnLevel>1</highestCollected.WardOnLevel>
          <totalTimeHeld.FireBallDash>515.5833602231</totalTimeHeld.FireBallDash>
          <totalTimeHeld.GainArmor>1272.46673303097</totalTimeHeld.GainArmor>
          <totalTimesFired.FireBallDash>4</totalTimesFired.FireBallDash>
          <totalTimesFired.GainArmor>5</totalTimesFired.GainArmor>
          <totalTimesVisited.blackbeach>1</totalTimesVisited.blackbeach>
          <totalTimesVisited.foggyswamp>1</totalTimesVisited.foggyswamp>
          <totalTimesVisited.rootjungle>1</totalTimesVisited.rootjungle>
          <totalTimesVisited.wispgraveyard>1</totalTimesVisited.wispgraveyard>
          <totalTimesCleared.blackbeach>1</totalTimesCleared.blackbeach>
          <totalTimesCleared.foggyswamp>1</totalTimesCleared.foggyswamp>
          <totalTimesCleared.wispgraveyard>1</totalTimesCleared.wispgraveyard>
        </fields>
      </statSheet>
      <itemAcquisitionOrder>CritGlasses SprintArmor Thorns PersonalShield BonusGoldPackOnKill BossDamageBonus StunChanceOnHit Bandolier SprintBonus Syringe ChainLightning StickyBomb BleedOnHit Mushroom BarrierOnKill IgniteOnKill Crowbar ScrapWhite FlatHealth SlowOnHit WardOnLevel</itemAcquisitionOrder>
      <itemStacks>
        <Bandolier>2</Bandolier>
        <BarrierOnKill>2</BarrierOnKill>
        <BleedOnHit>1</BleedOnHit>
        <BonusGoldPackOnKill>1</BonusGoldPackOnKill>
        <BossDamageBonus>2</BossDamageBonus>
        <ChainLightning>1</ChainLightning>
        <CritGlasses>1</CritGlasses>
        <Crowbar>1</Crowbar>
        <FlatHealth>1</FlatHealth>
        <IgniteOnKill>2</IgniteOnKill>
        <Mushroom>2</Mushroom>
        <PersonalShield>2</PersonalShield>
        <ScrapWhite>1</ScrapWhite>
        <SlowOnHit>2</SlowOnHit>
        <SprintArmor>1</SprintArmor>
        <SprintBonus>1</SprintBonus>
        <StickyBomb>1</StickyBomb>
        <StunChanceOnHit>3</StunChanceOnHit>
        <Syringe>2</Syringe>
        <Thorns>1</Thorns>
        <WardOnLevel>1</WardOnLevel>
      </itemStacks>
      <equipment>FireBallDash</equipment>
      <finalMessageToken>PLAYER_DEATH_QUOTE_9</finalMessageToken>
      <localPlayerIndex>0</localPlayerIndex>
      <userProfileFileName>c9031197-292c-4ee4-9fe6-6e68bd93ed5c</userProfileFileName>
    </PlayerInfo>
  </playerInfos>
</RunReport>